{
	"cmake" : 
	{
		"generator" : 
		{
			"multiConfig" : false,
			"name" : "Ninja"
		},
		"paths" : 
		{
			"cmake" : "/home/user064/.local/share/JetBrains/Toolbox/apps/clion/bin/cmake/linux/x64/bin/cmake",
			"cpack" : "/home/user064/.local/share/JetBrains/Toolbox/apps/clion/bin/cmake/linux/x64/bin/cpack",
			"ctest" : "/home/user064/.local/share/JetBrains/Toolbox/apps/clion/bin/cmake/linux/x64/bin/ctest",
			"root" : "/home/user064/.local/share/JetBrains/Toolbox/apps/clion/bin/cmake/linux/x64/share/cmake-3.27"
		},
		"version" : 
		{
			"isDirty" : false,
			"major" : 3,
			"minor" : 27,
			"patch" : 8,
			"string" : "3.27.8",
			"suffix" : ""
		}
	},
	"objects" : 
	[
		{
			"jsonFile" : "codemodel-v2-7e6a59067d3a9c48a608.json",
			"kind" : "codemodel",
			"version" : 
			{
				"major" : 2,
				"minor" : 6
			}
		},
		{
			"jsonFile" : "cache-v2-8d37631601fe5fd9a973.json",
			"kind" : "cache",
			"version" : 
			{
				"major" : 2,
				"minor" : 0
			}
		},
		{
			"jsonFile" : "cmakeFiles-v1-e082249ff77c1818f148.json",
			"kind" : "cmakeFiles",
			"version" : 
			{
				"major" : 1,
				"minor" : 0
			}
		},
		{
			"jsonFile" : "toolchains-v1-536a7eaeba1a33fdf7c1.json",
			"kind" : "toolchains",
			"version" : 
			{
				"major" : 1,
				"minor" : 0
			}
		}
	],
	"reply" : 
	{
		"cache-v2" : 
		{
			"jsonFile" : "cache-v2-8d37631601fe5fd9a973.json",
			"kind" : "cache",
			"version" : 
			{
				"major" : 2,
				"minor" : 0
			}
		},
		"cmakeFiles-v1" : 
		{
			"jsonFile" : "cmakeFiles-v1-e082249ff77c1818f148.json",
			"kind" : "cmakeFiles",
			"version" : 
			{
				"major" : 1,
				"minor" : 0
			}
		},
		"codemodel-v2" : 
		{
			"jsonFile" : "codemodel-v2-7e6a59067d3a9c48a608.json",
			"kind" : "codemodel",
			"version" : 
			{
				"major" : 2,
				"minor" : 6
			}
		},
		"toolchains-v1" : 
		{
			"jsonFile" : "toolchains-v1-536a7eaeba1a33fdf7c1.json",
			"kind" : "toolchains",
			"version" : 
			{
				"major" : 1,
				"minor" : 0
			}
		}
	}
}
